caninos_sdk/__init__.py
caninos_sdk/camera.py
caninos_sdk/i2c.py
caninos_sdk/labrador.py
caninos_sdk/pin.py
caninos_sdk/pwm.py
caninos_sdk/serial.py
tests/__init__.py
tests/test_gpio.py
tests/test_pwm.py
tests/test_sdk.py
caninos_sdk-0.5.0.dist-info/LICENSE
caninos_sdk-0.5.0.dist-info/METADATA
caninos_sdk-0.5.0.dist-info/WHEEL
caninos_sdk-0.5.0.dist-info/top_level.txt
caninos_sdk-0.5.0.dist-info/RECORD
