Metadata-Version: 2.1
Name: caninos-sdk
Version: 0.5.0
License-File: LICENSE
Requires-Dist: typer
Requires-Dist: rich
Requires-Dist: gpiod
Requires-Dist: pyserial
